agent/__init__.py
agent/base.py
agent/historystrategy.py
agent/llmclient.py
agent/schema.py
agent/core/__init__.py
agent/core/assitants.py
agent/core/base_assistant.py
agent/core/builder.py
agent/core/parallel_assistant.py
agent/tool_base/__init__.py
agent/tool_base/executable_tool.py
agent/tool_base/flexible_context.py
agent/tool_base/tool.py
agent/tools/__init__.py
delegateagent-0.1.0.dist-info/LICENSE
delegateagent-0.1.0.dist-info/METADATA
delegateagent-0.1.0.dist-info/WHEEL
delegateagent-0.1.0.dist-info/top_level.txt
delegateagent-0.1.0.dist-info/RECORD
