Metadata-Version: 2.1
Name: DelegateAgent
Version: 0.1.0
Summary: A delegation-centric multi-agent system framework for LLM-based autonomous systems
Author-email: BJTU Security Lab <qiangcas@gmail.com>
Maintainer-email: BJTU Security Lab <qiangcas@gmail.com>
License: MIT
Project-URL: Homepage, https://github.com/bjtu-SecurityLab/AgentHive
Project-URL: Documentation, https://github.com/bjtu-SecurityLab/AgentHive#readme
Project-URL: Repository, https://github.com/bjtu-SecurityLab/AgentHive
Project-URL: Bug Tracker, https://github.com/bjtu-SecurityLab/AgentHive/issues
Keywords: llm,agents,multi-agent-system,delegation,autonomous-systems,artificial-intelligence,machine-learning
Classifier: Development Status :: 3 - Alpha
Classifier: Intended Audience :: Developers
Classifier: Intended Audience :: Science/Research
Classifier: License :: OSI Approved :: MIT License
Classifier: Operating System :: OS Independent
Classifier: Programming Language :: Python :: 3
Classifier: Programming Language :: Python :: 3.8
Classifier: Programming Language :: Python :: 3.9
Classifier: Programming Language :: Python :: 3.10
Classifier: Programming Language :: Python :: 3.11
Classifier: Programming Language :: Python :: 3.12
Classifier: Topic :: Scientific/Engineering :: Artificial Intelligence
Classifier: Topic :: Software Development :: Libraries :: Python Modules
Requires-Python: >=3.8
License-File: LICENSE
Requires-Dist: openai>=1.0.0
Provides-Extra: dev
Requires-Dist: pytest>=7.0.0; extra == "dev"
Requires-Dist: pytest-asyncio>=0.21.0; extra == "dev"
Requires-Dist: black>=23.0.0; extra == "dev"
Requires-Dist: flake8>=6.0.0; extra == "dev"
Requires-Dist: mypy>=1.0.0; extra == "dev"
